rpgen/__init__.py
rpgen/character_type.py
rpgen/error_message.py
rpgen/password_generator.py
rpgen-0.0.3.dist-info/METADATA
rpgen-0.0.3.dist-info/WHEEL
rpgen-0.0.3.dist-info/licenses/LICENSE
rpgen-0.0.3.dist-info/RECORD
