Metadata-Version: 2.1
Name: rpgen
Version: 0.0.3
Summary: This generator makes it easy to set up a new password
Project-URL: Homepage, https://github.com/ldy9037
Author-email: Emadam <ldy9037@naver.com>
License-File: LICENSE
Classifier: License :: OSI Approved :: MIT License
Classifier: Operating System :: OS Independent
Classifier: Programming Language :: Python :: 3
Requires-Python: >=3.7
